row.py
setup.py
row.egg-info/PKG-INFO
row.egg-info/SOURCES.txt
row.egg-info/dependency_links.txt
row.egg-info/requires.txt
row.egg-info/top_level.txt